familiar/__init__.py
familiar/agents.py
familiar/cli.py
familiar/lint.py
familiar/py.typed
familiar/render.py
familiar/data/conjurings/core.md
familiar/data/conjurings/data.md
familiar/data/conjurings/docs.md
familiar/data/conjurings/frontend.md
familiar/data/conjurings/infra.md
familiar/data/conjurings/python.md
familiar/data/conjurings/rust.md
familiar/data/conjurings/sec.md
familiar/data/invocations/__noop__.md
familiar/data/invocations/add-ci.md
familiar/data/invocations/add-tests.md
familiar/data/invocations/audit.md
familiar/data/invocations/bootstrap-python.md
familiar/data/invocations/bootstrap-rust.md
familiar/data/invocations/code-review.md
familiar/data/invocations/explain.md
familiar/data/invocations/implement-feature.md
familiar/data/invocations/infra-change.md
familiar/data/invocations/performance.md
familiar/data/invocations/refactor.md
familiar/data/invocations/release.md
familiar/data/invocations/security-review.md
familiar/data/snippets/node/github-ci.yml
familiar/data/snippets/node/gitlab-ci.yml
familiar/data/snippets/python/github-ci.yml
familiar/data/snippets/python/gitlab-ci.yml
familiar/data/snippets/python/pyproject.toml
familiar/data/snippets/rust/Cargo.toml
familiar/data/snippets/rust/github-ci.yml
familiar/data/snippets/rust/gitlab-ci.yml
familiar_cli-0.3.1.dist-info/licenses/LICENSE
familiar_cli-0.3.1.dist-info/METADATA
familiar_cli-0.3.1.dist-info/WHEEL
familiar_cli-0.3.1.dist-info/entry_points.txt
familiar_cli-0.3.1.dist-info/top_level.txt
familiar_cli-0.3.1.dist-info/RECORD
