Metadata-Version: 2.4
Name: familiar-cli
Version: 0.3.1
Summary: compose and invoke ai agent prompts from reusable templates
Author-email: cyberwitchery lab <contact@cyberwitchery.com>
License-Expression: MIT
Project-URL: Homepage, https://github.com/cyberwitchery/familiar
Project-URL: Repository, https://github.com/cyberwitchery/familiar
Keywords: ai,agents,prompts,cli,codex,claude
Classifier: Development Status :: 3 - Alpha
Classifier: Environment :: Console
Classifier: Intended Audience :: Developers
Classifier: Operating System :: OS Independent
Classifier: Programming Language :: Python :: 3
Classifier: Programming Language :: Python :: 3.10
Classifier: Programming Language :: Python :: 3.11
Classifier: Programming Language :: Python :: 3.12
Classifier: Topic :: Software Development :: Code Generators
Requires-Python: >=3.10
License-File: LICENSE
Provides-Extra: dev
Requires-Dist: ruff; extra == "dev"
Requires-Dist: mypy; extra == "dev"
Requires-Dist: pytest; extra == "dev"
Requires-Dist: pytest-cov; extra == "dev"
Requires-Dist: bandit; extra == "dev"
Dynamic: license-file
